revolve2/simulators/mujoco_simulator/__init__.py
revolve2/simulators/mujoco_simulator/_abstraction_to_mujoco_mapping.py
revolve2/simulators/mujoco_simulator/_control_interface_impl.py
revolve2/simulators/mujoco_simulator/_local_simulator.py
revolve2/simulators/mujoco_simulator/_open_gl_vision.py
revolve2/simulators/mujoco_simulator/_render_backend.py
revolve2/simulators/mujoco_simulator/_scene_to_model.py
revolve2/simulators/mujoco_simulator/_simulate_manual_scene.py
revolve2/simulators/mujoco_simulator/_simulate_scene.py
revolve2/simulators/mujoco_simulator/_simulation_state_impl.py
revolve2/simulators/mujoco_simulator/py.typed
revolve2/simulators/mujoco_simulator/textures/__init__.py
revolve2/simulators/mujoco_simulator/textures/_checker.py
revolve2/simulators/mujoco_simulator/textures/_flat.py
revolve2/simulators/mujoco_simulator/textures/_gradient.py
revolve2/simulators/mujoco_simulator/viewers/__init__.py
revolve2/simulators/mujoco_simulator/viewers/_custom_mujoco_viewer.py
revolve2/simulators/mujoco_simulator/viewers/_native_mujoco_viewer.py
revolve2/simulators/mujoco_simulator/viewers/_viewer_type.py
revolve2_mujoco_simulator-1.2.4.dist-info/METADATA
revolve2_mujoco_simulator-1.2.4.dist-info/WHEEL
revolve2_mujoco_simulator-1.2.4.dist-info/RECORD
